nextnanopy/__init__.py
nextnanopy/commands.py
nextnanopy/defaults.py
nextnanopy/inputs.py
nextnanopy/outputs.py
nextnanopy/postprocess.py
nextnanopy/shapes.py
nextnanopy/msb/__init__.py
nextnanopy/msb/defaults.py
nextnanopy/msb/inputs.py
nextnanopy/msb/outputs.py
nextnanopy/negf/__init__.py
nextnanopy/negf/defaults.py
nextnanopy/negf/inputs.py
nextnanopy/negf/inputs_classic.py
nextnanopy/negf/outputs.py
nextnanopy/nn3/__init__.py
nextnanopy/nn3/defaults.py
nextnanopy/nn3/inputs.py
nextnanopy/nn3/outputs.py
nextnanopy/nnevo/__init__.py
nextnanopy/nnevo/defaults.py
nextnanopy/nnp/__init__.py
nextnanopy/nnp/assistants.py
nextnanopy/nnp/defaults.py
nextnanopy/nnp/inputs.py
nextnanopy/nnp/outputs.py
nextnanopy/nnp/shapes.py
nextnanopy/utils/__init__.py
nextnanopy/utils/config.py
nextnanopy/utils/datasets.py
nextnanopy/utils/formatting.py
nextnanopy/utils/misc.py
nextnanopy/utils/mycollections.py
nextnanopy/utils/plotting.py
nextnanopy/utils/shapes_deprecated.py
nextnanopy/utils/timer.py
nextnanopy/utils/styles/__init__.py
nextnanopy/utils/styles/nxt_style.mplstyle
nextnanopy-1.0.3.dist-info/licenses/LICENSE
nextnanopy-1.0.3.dist-info/METADATA
nextnanopy-1.0.3.dist-info/WHEEL
nextnanopy-1.0.3.dist-info/top_level.txt
nextnanopy-1.0.3.dist-info/RECORD
