Metadata-Version: 2.4
Name: nextnanopy
Version: 1.0.3
Summary: Useful tools to interface the nextnano software (https://www.nextnano.com/)
Home-page: https://github.com/nextnanopy/nextnanopy
Author: nextnano GmbH
Author-email: python@nextnano.com
License: BSD-3-Clause
Keywords: nextnano
Classifier: Programming Language :: Python :: 3
Classifier: License :: OSI Approved :: BSD License
Classifier: Operating System :: OS Independent
Classifier: Intended Audience :: Customer Service
Classifier: Intended Audience :: Developers
Classifier: Intended Audience :: Education
Classifier: Intended Audience :: Science/Research
Classifier: Natural Language :: English
Requires-Python: >=3.10
License-File: LICENSE
Requires-Dist: numpy>=1.18
Requires-Dist: pyvista>=0.27
Provides-Extra: gdspy
Requires-Dist: gdspy>=1.6; extra == "gdspy"
Provides-Extra: matplotlib
Requires-Dist: matplotlib>=3.2; extra == "matplotlib"
Provides-Extra: cycler
Requires-Dist: cycler>=0.10; extra == "cycler"
Provides-Extra: shapely
Requires-Dist: shapely>=1.7; extra == "shapely"
Dynamic: author
Dynamic: author-email
Dynamic: classifier
Dynamic: description
Dynamic: description-content-type
Dynamic: home-page
Dynamic: keywords
Dynamic: license
Dynamic: license-file
Dynamic: provides-extra
Dynamic: requires-dist
Dynamic: requires-python
Dynamic: summary
